Renjian3rd/README.md
Renjian3rd/__init__.py
Renjian3rd/__main__.py
Renjian3rd/file.epub
Renjian3rd/index.html
Renjian3rd/css/__init__.py
Renjian3rd/css/annotations.css
Renjian3rd/css/main.css
Renjian3rd/css/normalize.css
Renjian3rd/css/popup.css
Renjian3rd/font/__init__.py
Renjian3rd/font/fontello.eot
Renjian3rd/font/fontello.svg
Renjian3rd/font/fontello.ttf
Renjian3rd/font/fontello.woff
Renjian3rd/img/__init__.py
Renjian3rd/img/annotator-glyph-sprite.png
Renjian3rd/img/annotator-icon-sprite.png
Renjian3rd/img/apple-touch-icon.png
Renjian3rd/img/cancelfullscreen.png
Renjian3rd/img/close.png
Renjian3rd/img/fullscreen.png
Renjian3rd/img/loader.gif
Renjian3rd/img/menu-icon.png
Renjian3rd/img/save.png
Renjian3rd/img/saved.png
Renjian3rd/img/settings-s.png
Renjian3rd/img/settings.png
Renjian3rd/img/star.png
Renjian3rd/js/__init__.py
Renjian3rd/js/epub.js
Renjian3rd/js/epub.min.js
Renjian3rd/js/epub.min.map
Renjian3rd/js/hooks.min.js
Renjian3rd/js/hooks.min.map
Renjian3rd/js/reader.js
Renjian3rd/js/reader.js.map
Renjian3rd/js/reader.min.js
Renjian3rd/js/reader.min.map
Renjian3rd/js/hooks/__init__.py
Renjian3rd/js/hooks/extensions/__init__.py
Renjian3rd/js/hooks/extensions/highlight.js
Renjian3rd/js/libs/__init__.py
Renjian3rd/js/libs/jquery.min.js
Renjian3rd/js/libs/localforage.min.js
Renjian3rd/js/libs/screenfull.js
Renjian3rd/js/libs/screenfull.min.js
Renjian3rd/js/libs/zip.min.js
Renjian3rd/js/plugins/__init__.py
Renjian3rd/js/plugins/hypothesis.js
Renjian3rd/js/plugins/search.js
renjian_3rd-2024.3.5.0.dist-info/METADATA
renjian_3rd-2024.3.5.0.dist-info/WHEEL
renjian_3rd-2024.3.5.0.dist-info/entry_points.txt
renjian_3rd-2024.3.5.0.dist-info/top_level.txt
renjian_3rd-2024.3.5.0.dist-info/RECORD
